{
    "Ar36": {
        "error": 0.0008576804392154516, 
        "filter_outliers_dict": {
            "filter_outliers": true, 
            "iterations": 2, 
            "std_devs": 2
        }, 
        "fit": "Parabolic", 
        "value": 0.16359960297171577
    }, 
    "Ar37": {
        "error": 0.013031756868263899, 
        "filter_outliers_dict": {
            "filter_outliers": true, 
            "iterations": 2, 
            "std_devs": 2
        }, 
        "fit": "linear", 
        "value": -0.38239636579345027
    }, 
    "Ar38": {
        "error": 0.012863662985982453, 
        "filter_outliers_dict": {
            "filter_outliers": true, 
            "iterations": 2, 
            "std_devs": 2
        }, 
        "fit": "linear", 
        "value": 0.037106850178196864
    }, 
    "Ar39": {
        "error": 0.025548823784858038, 
        "filter_outliers_dict": {
            "filter_outliers": true, 
            "iterations": 2, 
            "std_devs": 2
        }, 
        "fit": "Parabolic", 
        "value": 8.186090577508638
    }, 
    "Ar40": {
        "error": 0.025155349588534576, 
        "filter_outliers_dict": {
            "filter_outliers": true, 
            "iterations": 2, 
            "std_devs": 2
        }, 
        "fit": "Parabolic", 
        "value": 63.335551858186975
    }
}