{
    "Ar36": {
        "error": 0.0005371778769722304, 
        "fit": "previous", 
        "references": [
            {
                "exclude": false, 
                "record_id": "bu-NF-F-194"
            }
        ], 
        "value": 0.06054112884651233
    }, 
    "Ar37": {
        "error": 0.010970726657829017, 
        "fit": "previous", 
        "references": [
            {
                "exclude": false, 
                "record_id": "bu-NF-F-194"
            }
        ], 
        "value": 0.01883917752326858
    }, 
    "Ar38": {
        "error": 0.013780691144425927, 
        "fit": "previous", 
        "references": [
            {
                "exclude": false, 
                "record_id": "bu-NF-F-194"
            }
        ], 
        "value": 0.006876522636937749
    }, 
    "Ar39": {
        "error": 0.023378969196390192, 
        "fit": "previous", 
        "references": [
            {
                "exclude": false, 
                "record_id": "bu-NF-F-194"
            }
        ], 
        "value": -0.0018676922401046278
    }, 
    "Ar40": {
        "error": 0.02203258562878044, 
        "fit": "previous", 
        "references": [
            {
                "exclude": false, 
                "record_id": "bu-NF-F-194"
            }
        ], 
        "value": 17.818210835545596
    }
}